_mpy_shed/IRQs.pyi
_mpy_shed/__init__.pyi
_mpy_shed/_collections_abc.pyi
_mpy_shed/blockdevice.pyi
_mpy_shed/buffer_mp.pyi
_mpy_shed/io_modes.pyi
_mpy_shed/io_mp.pyi
_mpy_shed/mp_available.pyi
_mpy_shed/mp_implementation.py
_mpy_shed/neopixelbase.pyi
_mpy_shed/pathlike.pyi
_mpy_shed/subscriptable.pyi
_mpy_shed/time_mp.pyi
_mpy_shed/collections/__init__.pyi
_mpy_shed/collections/abc.pyi
stdlib/VERSIONS
stdlib/__future__.pyi
stdlib/_ast.pyi
stdlib/_codecs.pyi
stdlib/_collections_abc.pyi
stdlib/_decimal.pyi
stdlib/abc.pyi
stdlib/array.pyi
stdlib/builtins.pyi
stdlib/enum.pyi
stdlib/io.pyi
stdlib/re.pyi
stdlib/sre_compile.pyi
stdlib/sre_constants.pyi
stdlib/sre_parse.pyi
stdlib/ssl.pyi
stdlib/struct.pyi
stdlib/types.pyi
stdlib/typing.pyi
stdlib/typing_extensions.pyi
stdlib/_typeshed/README.md
stdlib/_typeshed/__init__.pyi
stdlib/_typeshed/dbapi.pyi
stdlib/_typeshed/importlib.pyi
stdlib/_typeshed/wsgi.pyi
stdlib/_typeshed/xml.pyi
stdlib/asyncio/__init__.pyi
stdlib/asyncio/base_events.pyi
stdlib/asyncio/base_futures.pyi
stdlib/asyncio/base_tasks.pyi
stdlib/asyncio/constants.pyi
stdlib/asyncio/coroutines.pyi
stdlib/asyncio/events.pyi
stdlib/asyncio/exceptions.pyi
stdlib/asyncio/format_helpers.pyi
stdlib/asyncio/futures.pyi
stdlib/asyncio/locks.pyi
stdlib/asyncio/log.pyi
stdlib/asyncio/micropython.pyi
stdlib/asyncio/mixins.pyi
stdlib/asyncio/proactor_events.pyi
stdlib/asyncio/protocols.pyi
stdlib/asyncio/queues.pyi
stdlib/asyncio/readme.md
stdlib/asyncio/runners.pyi
stdlib/asyncio/selector_events.pyi
stdlib/asyncio/sslproto.pyi
stdlib/asyncio/staggered.pyi
stdlib/asyncio/streams.pyi
stdlib/asyncio/tasks.pyi
stdlib/asyncio/threads.pyi
stdlib/asyncio/timeouts.pyi
stdlib/asyncio/transports.pyi
stdlib/asyncio/trsock.pyi
stdlib/collections/__init__.pyi
stdlib/collections/abc.pyi
stdlib/json/__init__.pyi
stdlib/os/__init__.pyi
stdlib/sys/__init__.pyi
stubs/mypy-extensions/mypy_extensions.pyi
micropython_stdlib_stubs-1.26.0.post2.dist-info/METADATA
micropython_stdlib_stubs-1.26.0.post2.dist-info/WHEEL
micropython_stdlib_stubs-1.26.0.post2.dist-info/licenses/LICENSE.md
micropython_stdlib_stubs-1.26.0.post2.dist-info/licenses/LICENSE_typeshed
micropython_stdlib_stubs-1.26.0.post2.dist-info/RECORD
