Metadata-Version: 2.4
Name: micropython-stdlib-stubs
Version: 1.26.0.post2
Summary: Micropython stdlib is a reduced and augmented copy of typeshed's stdlib for use by MicroPython stub packages
Project-URL: homepage, https://github.com/josverl/micropython-stubs#micropython-stubs
Project-URL: documentation, https://micropython-stubs.readthedocs.io/
Project-URL: repository, https://github.com/josverl/micropython-stubs
Author-email: Jos Verlinde <josverl@users.noreply.github.com>
License-Expression: MIT
License-File: LICENSE.md
License-File: LICENSE_typeshed
Classifier: Development Status :: 5 - Production/Stable
Classifier: Operating System :: OS Independent
Classifier: Programming Language :: Python
Classifier: Programming Language :: Python :: 3
Classifier: Programming Language :: Python :: 3 :: Only
Classifier: Programming Language :: Python :: Implementation :: MicroPython
Classifier: Topic :: Software Development :: Build Tools
Classifier: Topic :: Text Editors :: Integrated Development Environments (IDE)
Classifier: Typing :: Stubs Only
Requires-Python: >=3.7
